{
  "hash": "5bfe6510",
  "configHash": "3c6940c8",
  "lockfileHash": "e3b0c442",
  "browserHash": "565992aa",
  "optimized": {
    "vue": {
      "src": "../../../../node_modules/vue/dist/vue.runtime.esm-bundler.js",
      "file": "vue.js",
      "fileHash": "e4252c01",
      "needsInterop": false
    },
    "vitepress > @vue/devtools-api": {
      "src": "../../../../node_modules/@vue/devtools-api/dist/index.js",
      "file": "vitepress___@vue_devtools-api.js",
      "fileHash": "ecd5b6d3",
      "needsInterop": false
    },
    "vitepress > @vueuse/core": {
      "src": "../../../../node_modules/@vueuse/core/index.mjs",
      "file": "vitepress___@vueuse_core.js",
      "fileHash": "ec61f2aa",
      "needsInterop": false
    },
    "@theme/index": {
      "src": "../../../../node_modules/vitepress/dist/client/theme-default/index.js",
      "file": "@theme_index.js",
      "fileHash": "3305ff32",
      "needsInterop": false
    }
  },
  "chunks": {
    "chunk-37WC2YIS": {
      "file": "chunk-37WC2YIS.js"
    },
    "chunk-BCMC4SMG": {
      "file": "chunk-BCMC4SMG.js"
    }
  }
}